vaeesr/__init__.py
vaeesr/evaluation.py
vaeesr/loss.py
vaeesr/main.py
vaeesr/models.py
vaeesr/preprocessing.py
vaeesr/training.py
vaeesr/utils.py
vaeesr-0.0.2.dist-info/LICENSE
vaeesr-0.0.2.dist-info/METADATA
vaeesr-0.0.2.dist-info/WHEEL
vaeesr-0.0.2.dist-info/top_level.txt
vaeesr-0.0.2.dist-info/RECORD
