Metadata-Version: 2.1
Name: vaeesr
Version: 0.0.2
Summary: Using the latent space of a variational autoencoder to perform symbolic regression by sampling equations.
Author: Lisa Artmann
Author-email: lisaartmann01@gmail.com
Keywords: Symbolic Regression,Equation Discovery,Variational Autoencoder
Classifier: Development Status :: 3 - Alpha
Classifier: Intended Audience :: Science/Research
Classifier: Intended Audience :: Developers
Classifier: Intended Audience :: Education
Classifier: Programming Language :: Python :: 3
Classifier: Operating System :: MacOS :: MacOS X
Classifier: Operating System :: Microsoft :: Windows
Classifier: License :: OSI Approved :: MIT License
Classifier: Topic :: Scientific/Engineering :: Artificial Intelligence
License-File: LICENSE
Requires-Dist: equation-tree
Requires-Dist: numpy
Requires-Dist: tqdm
Requires-Dist: torch
Requires-Dist: pandas
Requires-Dist: sympy
Requires-Dist: scipy
Requires-Dist: scikit-learn
Requires-Dist: pyro-ppl
